metropack/__init__.py
metropack/draw.py
metropack/metros.py
metropack/pack.py
metropack-0.1.1.dist-info/DESCRIPTION.rst
metropack-0.1.1.dist-info/METADATA
metropack-0.1.1.dist-info/metadata.json
metropack-0.1.1.dist-info/pbr.json
metropack-0.1.1.dist-info/RECORD
metropack-0.1.1.dist-info/top_level.txt
metropack-0.1.1.dist-info/WHEEL
